emg/.DS_Store
emg/__init__.py
emg/generator.py
emg/py.typed
emg/requirements.txt
emg-0.1.8.dist-info/WHEEL
emg-0.1.8.dist-info/METADATA
emg-0.1.8.dist-info/RECORD
