Metadata-Version: 2.3
Name: emg
Version: 0.1.8
Summary: Python library for generating melodies using the concept of Eulerian paths
Author: Chinmay Kakatkar
License: MIT License
Requires-Dist: matplotlib>=3.10.5
Requires-Dist: midi2audio>=0.1.1
Requires-Dist: midiutil>=1.2.1
Requires-Dist: networkx>=3.5
Requires-Python: >=3.12
Project-URL: Homepage, https://github.com/ckstash/emg
